SpheroScan/UI_com.py
SpheroScan/__init__.py
SpheroScan/app.py
SpheroScan/helperFun.py
SpheroScan/launcher.py
SpheroScan/main.py
SpheroScan/plots.py
SpheroScan/pred_time.py
SpheroScan/prediction.py
SpheroScan-0.0.10.dist-info/LICENSE.toml
SpheroScan-0.0.10.dist-info/METADATA
SpheroScan-0.0.10.dist-info/WHEEL
SpheroScan-0.0.10.dist-info/top_level.txt
SpheroScan-0.0.10.dist-info/RECORD
