Metadata-Version: 2.1
Name: SpheroScan
Version: 0.0.10
Summary: A User-Friendly Deep Learning Tool for Spheroid Image Analysis.
Home-page: https://github.com/FunctionalUrology/SpheroScan.git
Author: Akshay
Author-email: akshaysuhag1996@gmail.com
Project-URL: Bug Tracker, https://github.com/FunctionalUrology/SpheroScan/issues
Classifier: Programming Language :: Python :: 3
Classifier: License :: OSI Approved :: MIT License
Classifier: Operating System :: OS Independent
Requires-Python: >=3.10
License-File: LICENSE.toml
Requires-Dist: dash
Requires-Dist: pandas
Requires-Dist: numpy
Requires-Dist: scipy
Requires-Dist: bokeh
Requires-Dist: plotly
Requires-Dist: zipfile36
Requires-Dist: opencv-python
Requires-Dist: matplotlib
Requires-Dist: subprocess.run
Requires-Dist: gunicorn
Requires-Dist: dash-bootstrap-components
Requires-Dist: dash-uploader
Requires-Dist: dash-loading-spinners
